LICENSE.TXT
README.md
setup.py
cli/vre_video_player.py
vre_video/__init__.py
vre_video/utils.py
vre_video/vre_video.py
vre_video.egg-info/PKG-INFO
vre_video.egg-info/SOURCES.txt
vre_video.egg-info/dependency_links.txt
vre_video.egg-info/requires.txt
vre_video.egg-info/top_level.txt
vre_video/readers/__init__.py
vre_video/readers/fd_frame_reader.py
vre_video/readers/ffmpeg_frame_reader.py
vre_video/readers/frame_reader.py
vre_video/readers/numpy_frame_reader.py
vre_video/readers/pil_frame_reader.py
vre_video/writers/__init__.py
vre_video/writers/ffmpeg_frame_writer.py
vre_video/writers/frame_writer.py
vre_video/writers/numpy_frame_writer.py
vre_video/writers/pil_frame_writer.py