Metadata-Version: 2.1
Name: vre-video
Version: 0.5.1
Summary: Video Representations Extractor (VRE) Video reader
Home-page: https://gitlab.com/video-representations-extractor/vre-video
License: MIT
Requires-Python: >=3.8
License-File: LICENSE.TXT
Requires-Dist: numpy>=1.21.6
Requires-Dist: Pillow>=11.3.0
Requires-Dist: loggez>=0.7.6
Requires-Dist: tqdm>=4.66.5
